sanfis/__init__.py
sanfis/helpers.py
sanfis/plottingtools.py
sanfis/sanfis.py
sanfis/datagenerators/__init__.py
sanfis/datagenerators/anfis_generator.py
sanfis/datagenerators/sanfis_generator.py
sanfis-0.1.0.dist-info/LICENSE
sanfis-0.1.0.dist-info/METADATA
sanfis-0.1.0.dist-info/WHEEL
sanfis-0.1.0.dist-info/top_level.txt
sanfis-0.1.0.dist-info/RECORD
