Metadata-Version: 2.1
Name: sanfis
Version: 0.1.0
Summary: Implementation to the State-Adaptive Neurofuzzy Inference System (S-ANFIS) network
Home-page: https://github.com/gregorLen/S-ANFIS-PyTorch
Author: Gregor Lenhard
Author-email: gregor.lenhard92@gmail.com
License: MIT License
Platform: UNKNOWN
License-File: LICENSE
Requires-Dist: numpy
Requires-Dist: seaborn
Requires-Dist: pandas
Requires-Dist: matplotlib
Requires-Dist: tqdm
Requires-Dist: scikit-learn
Requires-Dist: tensorboard
Provides-Extra: dev
Requires-Dist: pytest ; extra == 'dev'
